quakesee_web/__init__.py
quakesee_web/about_web.py
quakesee_web/app.py
quakesee_web/eqcat_fetcher_web.py
quakesee_web/logo.png
quakesee_web/wave_fetcher_web.py
quakesee_web-0.1.0.dist-info/LICENSE
quakesee_web-0.1.0.dist-info/METADATA
quakesee_web-0.1.0.dist-info/WHEEL
quakesee_web-0.1.0.dist-info/entry_points.txt
quakesee_web-0.1.0.dist-info/top_level.txt
quakesee_web-0.1.0.dist-info/RECORD
